{
  "slug" : "9298-foundations-precision-flow",
  "meta" : {
    "slug" : "9298-foundations-precision-flow",
    "title" : "kae3g 9298: Foundations of Precision Flow",
    "filename" : "9298-foundations-precision-flow.md",
    "series" : "Coldriver Heal",
    "source-dir" : "hidden"
  },
  "html" : "<h1>Foundations of Precision Flow</h1><p><em>On building systems that endure through mathematical clarity and ecological wisdom</em><h2></h2></p><h2>The Vision: Coldriver Heal</h2><p>In the realm of community-owned computing, we seek systems that endure. Not for months or years, but for generations. Systems that can be understood completely, verified formally, and regenerated eternally. Systems that maintain themselves, that stay consistent, that preserve their integrity across decades of growth and change.</p><p>This essay introduces the philosophical foundation for such systems. We call it <strong>Coldriver Heal</strong>—a synthesis of mathematical precision and ecological wisdom that guides our approach to building software that lasts.</p><p>The name itself carries meaning in layers. <strong>Cold</strong> refers to Hilbert's mathematical rigor, to crystalline specifications with well-formed structure, to axiomatic foundations we can prove correct, to formal systems with clear rules. Water at four degrees Celsius is most dense, most organized, most mature. This is crystalline precision—the temperature at which clarity takes its most ordered form, where structure emerges from flow. Gerald Pollack's research on the \"fourth phase of water\" reveals this structured state: water that organizes into liquid crystalline layers, more ordered than regular liquid yet more fluid than ice. EZ water (Exclusion Zone water) demonstrates that order and flow aren't opposites but partners—structure enabling movement, precision enabling adaptability.</p><p><strong>Water</strong> refers to Schauberger's ecological flow, to natural vortices that organize chaos, to implosion over explosion, efficiency over waste. It means full cycles that regenerate continuously, movement that spirals rather than plods linearly forward. Water finds its path, adapts to terrain, yet always follows immutable physical laws.</p><p><strong>Heal</strong> means the restoration of community-owned computing. It means completing dependency chains, closing open loops, returning to source specifications. It means regenesis—continuous renewal from enduring specs, not one-time genesis but ongoing regeneration.</p><p>The Coldriver heals through precision flow. It is directed, mathematical clarity that follows natural patterns of regeneration. It is crystalline water finding its course, carving channels that last centuries.<h2></h2></p><h2>Hilbert's Axiomatic Foundation</h2><p>David Hilbert, born in 1862, died in 1943, lived through two world wars and witnessed the birth of modern computing. But his revolutionary question predated all of that. What if, he asked, we could reduce all mathematical truth to a small set of axioms and rules? What if we could prove consistency, completeness, decidability? What if mathematics itself could be formalized so completely that a machine could verify every truth?</p><p>His program, though limited by Gödel's incompleteness theorems, gave us a powerful framework. Start with crystalline rules—well-formed, unchanging. Derive everything else formally. Build systems where every statement traces back to indisputable axioms. This is the Hilbert approach: axiomatization, where you define your base truths; formalization, where you express all operations as symbol manipulations; proof, where you show that derived theorems follow logically from axioms; consistency, where you prove the system doesn't contradict itself; and completeness, where you show that all true statements are provable.</p><p>Gödel proved that the last part—completeness—is impossible for any system powerful enough to encode arithmetic. There will always be true statements that cannot be proven within the system. But this limitation doesn't diminish the power of Hilbert's approach. It clarifies it. We build formal systems knowing their limits, which makes them more trustworthy, not less.</p><p>Consider a Hilbert space. It is an abstract mathematical structure, an infinite-dimensional vector space with an inner product. It provides a stage for operations, the space itself. It provides operators that transform states. It guarantees completeness, meaning every Cauchy sequence converges. It enforces orthogonality, meaning independence between basis vectors. These are not just mathematical curiosities. They are the foundations of quantum mechanics, signal processing, and functional analysis.</p><p>And we see Hilbert-like structures everywhere in computing. Nock's twelve rules form an axiomatic basis for computation, irreducible operations from which all programs derive. Git commits are formal derivations from previous states, each cryptographically hashed, each provably descended from what came before. Type systems provide proofs of program properties, guaranteeing at compile time that certain errors cannot occur at runtime. Formal verification demonstrates consistency, showing that a system's implementation matches its specification.</p><p>This is what we mean by crystalline precision. Well-formed specifications that don't drift with fashion. Formal proofs instead of empirical testing alone. Axiomatic clarity where every operation traces to fundamentals. Mathematical certainty within defined domains. This is the crystalline structure in Coldriver Heal—the bedrock that doesn't shift, the ordered foundation beneath the code.<h2></h2></p><h2>Schauberger's Natural Intelligence</h2><p>Viktor Schauberger, born in 1885, died in 1958, was an Austrian forester who spent his life observing water in its natural state. Mountain streams, untouched by human intervention, flowing through ancient forests. What he saw challenged the engineering orthodoxy of his time and offers us, today, a different way to think about systems.</p><p>His method was simple. Comprehend and copy nature. Observe natural systems, understand their principles, and then copy their patterns in your designs. Don't impose human abstractions on reality. Let reality teach you its ways.</p><p>He noticed that natural water doesn't flow straight. It curves, meanders, creates spiral patterns. Vortices form spontaneously. These spirals are not accidents of terrain but fundamental to water's health. They self-organize from chaos into stable structures. They draw air into water, oxygenating without pumps or energy input. They create zones of different temperature and pressure within the flow. They maintain the water's vitality and carrying capacity. Water that spirals stays alive. Water forced straight grows stagnant, loses energy, cannot sustain life.</p><p>He noticed that temperature gradients matter profoundly. Water at four degrees Celsius is most dense. This is water's mature temperature, its most organized state. When water flows through forests, shade keeps it cool. Cool water penetrates soil more easily, enabling the full water cycle. It carries more sediment, shaping rivers through their stones. It maintains biological life better. It flows with less friction. Nature's designs optimize for these patterns—cool, shaded, meandering flows that sustain themselves for centuries.</p><p>He noticed that conventional engineering uses explosion. Push outward. Apply pressure. Force through resistance. Burn fuel to overcome friction. This is the paradigm of industrial civilization—brute force applied to natural systems until they submit or break.</p><p>Schauberger showed another way. Implosion. Pull inward. Create suction. Allow natural flow. He built spiral pipes that reduced friction instead of fighting it. He designed vortex generators that purified water without chemicals, using only the water's own motion. He invented log flumes that carried even heavy timber downstream through spiraling water channels, using gravity and geometry where others needed steam engines.</p><p>And he understood water cycles. There are full cycles and half cycles. A full cycle is healthy, regenerative. Rain falls on cool, shaded soil. Water penetrates deeply, recharging groundwater. Springs emerge, feeding streams that flow to rivers that reach the sea. Evaporation creates clouds that bring more rain. The cycle continues indefinitely, self-sustaining, no external energy required.</p><p>A half cycle is degraded, extractive. Deforestation removes shade. Rain falls on hot, exposed ground. Water runs off without penetrating, causing floods downstream and drought upstream. The water table drops. Springs dry up. Less evaporation means less rain. Desertification accelerates. The cycle breaks, and you must pump water with diesel, irrigate with concrete channels, and watch as the land dies.</p><p>This is what we mean by natural patterns. Vortices, spirals, meandering paths that look inefficient to the linear mind but prove supremely efficient over time. Regenerative cycles that close loops, that waste nothing, that sustain themselves across generations. Implosion as design principle, reducing friction through geometry rather than overwhelming it with force. Temperature sensitivity, recognizing that cool means mature, organized, ready to flow with minimal resistance.</p><p>This is the water in Coldriver Heal—the flow that follows nature's proven patterns, the wisdom of four billion years of evolution encoded in how streams carve stone.<h2></h2></p><h2>Codeberg: The Precision Forge</h2><p>Before we synthesize Hilbert and Schauberger, let me give you a concrete technical example. Enter Codeberg—the first manifestation of Coldriver Heal principles in our stack. Why Codeberg first? Because community ownership begins with where your code lives.</p><p>GitHub is centralized, proprietary, subject to corporate whims and geopolitical pressures. One day your code is there, the next day sanctions or policy changes make it inaccessible. Self-hosted Git solves centralization but creates isolation and high maintenance burden. You become your own sysadmin, managing servers, backups, security patches, with no community to share the load.</p><p>Codeberg offers a third way. Federated, open-source, community-governed. Based on Forgejo, itself a fork of Gitea, ensuring that no single entity controls the platform. Hosted by a German non-profit, respecting European privacy laws. Free for all users, funded by donations, no artificial limits or premium tiers. This is where sovereignty meets practicality.</p><p>And Codeberg embodies both Hilbert's precision and Schauberger's flow.</p><p>Git itself is Hilbert-like. Consider its structure as a formal system. Axioms are blobs, trees, and commits—immutable objects that form the irreducible elements. Operators are add, commit, merge, rebase—transformations that move from one state to another. Every commit is a formal derivation from a previous state, cryptographically hashed to prove descent. Consistency is guaranteed by those hashes—no hidden changes can exist without detection. This is mathematical precision applied to code history.</p><p>Forgejo, the software behind Codeberg, adds a verification layer. Formal interfaces through REST API with clear contracts. Permission systems that provide provable access control. Audit logs where every action is recorded, traceable back to actors and timestamps. This is infrastructure built on explicit rules, not implicit trust.</p><p>But Codeberg also embodies Schauberger's flow. Consider Woodpecker CI, the continuous integration system. It functions as a purification vortex. Code enters as raw input. It spirals through test stages—unit tests, integration tests, linting, security scans. Each stage creates a different zone of pressure, catching different classes of errors. Dependencies and checks are drawn in like air into water. Chaos self-organizes into stable build artifacts. The code that emerges has been verified, purified by motion through the vortex.</p><p>Git's branching and merging patterns mirror natural water cycles. Source branches are springs, the origin of fresh work. Feature branches are tributaries, each exploring different terrain. Pull requests are confluence points where flows meet and merge. The main branch is the river, carrying accumulated work forward. Releases are the delta reaching the sea, stable points of deployment. Tags are evaporation into persistent reference, markers that endure. New branches are condensation and rain, the cycle beginning again. Closed loop. Regenerative. Nothing lost.</p><p>And Codeberg doesn't monopolize. It federates. Multiple instances exist, each serving different communities, different watersheds. They can communicate through ActivityPub, flowing data between sovereign domains. Each instance is independent yet connected, like natural water systems—distinct watersheds that nonetheless participate in the global hydrologic cycle.</p><p>Codeberg heals by breaking vendor lock-in, restoring sovereignty to developers. It provides deterministic builds through CI as verification vortex. It enables eternal regeneration through Git's immutable history. It supports federation, distributing control instead of centralizing it.</p><p>This is our first technical anchor—the precision forge where code flows through verification vortices and emerges purified, ready for the next stage of the journey.<h2></h2></p><h2>Helium Network: Democratized Connectivity</h2><p>If Codeberg manifests Coldriver Heal principles for community-owned code, then <a href='https://www.helium.com/'>Helium Network</a> demonstrates them for community-owned communications. The parallel is precise and illuminating.</p><p>Consider the problem Helium solves. Traditional wireless is centralized, controlled by a handful of corporations and government-granted spectrum monopolies. One carrier decides where coverage exists. One entity monitors your data. One corporation controls access. This is the same pattern we rejected with GitHub—centralized control of critical infrastructure.</p><p>Helium offers a third way for connectivity. Democratized, user-deployed, privacy-preserving. Anyone can deploy hotspots where coverage is needed. Within minutes, IoT devices, phones, and computers connect to the Helium network. No permission required. No monthly negotiations with carriers. No artificial coverage maps drawn in distant corporate offices.</p><p>Their principle is clear: \"Build The People's Network.\" This is community ownership extended from code to communication, from what you build to how you connect.</p><p>And Helium embodies both Hilbert's precision and Schauberger's flow.</p><p>Consider the Hilbert-like structure. Axioms are the Hotspots—plug-and-play devices with fixed, verifiable specifications. Operators are the deployment actions: install hotspot, connect to power and internet, broadcast coverage. Every deployment is a formal derivation—cryptographically secured on the blockchain, provably owned by the deployer. Consistency comes through fixed protocols—devices that comply work reliably, devices that don't provide clear diagnostics. This is mathematical precision applied to wireless infrastructure.</p><p>By 2025, the hardware ecosystem has matured. Multiple hotspot manufacturers (Bobcat, RAK, Nebra, SenseCAP) produce Helium-compatible radios, creating a robust, decentralized hardware supply chain. Indoor and outdoor models serve different needs—5G for mobile coverage, LoRaWAN for IoT sensors. No single vendor controls the physical layer. This is community ownership extending to the hardware itself.</p><p>The network adds verification through mathematical proof. Formal interface through encrypted channels with clear contracts. Permission systems providing provable access control—you own your hotspot, you control your coverage. Audit through blockchain ledger (HNT token rewards). Infrastructure built on explicit rules, not implicit trust in carrier benevolence.</p><p>The Proof-of-Coverage system uses sophisticated algorithms to reward useful coverage while penalizing redundant or poorly placed hotspots. This is formal verification applied to physical infrastructure—nodes prove they provide value, not just that they're powered on. The network optimizes itself through mathematical incentives, not corporate planning.</p><p>But Helium also embodies Schauberger's organic flow. Consider how the network grows. Users see coverage gaps and deploy hotspots to fill them. This is like rainfall patterns showing where water naturally wants to flow. Helium coverage follows organic demand—need drives deployment, not corporate profit optimization. The network emerges from the ground up, from actual usage patterns, creating a living map of connectivity shaped by real human requirements.</p><p>The deployment pattern mirrors natural colonization. Individual hotspots are like pioneer species, first plants in new soil. They broadcast coverage in all directions—LoRaWAN reaching miles for IoT sensors, 5G covering neighborhoods for mobile devices. As more hotspots deploy nearby, coverage zones overlap, creating resilient networks. Density increases where usage is highest. This is how ecosystems expand, how mycelial networks grow beneath forests, how natural systems self-organize in response to environmental pressures.</p><p>Helium's architecture follows vortex principles. Each hotspot is a spiral point, drawing devices into connectivity, providing services through encrypted channels, maintaining zones of access. Multiple hotspots create overlapping coverage—areas of strong signal, areas of transition, creating organic gradients rather than hard boundaries. The network breathes with usage, expanding during high demand, stable during low.</p><p>The economic model completes the regenerative cycle. Users deploy hotspots (spring water from source). Devices access coverage (flow downstream). HNT token rewards return to deployers (evaporation and condensation, value cycling back to infrastructure providers). New hotspots deploy where demand exists (rain falling where water is needed). Closed loop. Self-sustaining. No extractive intermediary taking permanent cut. This is full-cycle economics applied to communications.</p><p>Helium expands connectivity options. Rural areas can deploy their own networks exactly where needed. Businesses can guarantee reliable IoT sensors work, growing their operations with flexible infrastructure. Industrial sites get robust communications for autonomous vehicles and mission-critical operations. The network provides coverage that grows organically from community needs.</p><p>And Helium integrates with Starlink, extending the principle. Starlink provides internet backbone (the groundwater table, deep and reliable). Helium provides local wireless access (the springs and streams that make connectivity usable). Together they create complete community-owned connectivity—reduced dependency on terrestrial ISPs and cellular carriers, more control from satellite to device.</p><p>For practical adoption, the Helium Mobile service offers cellular plans that use the community hotspot network when available, falling back to traditional carriers when needed. This isn't compromise. It's pragmatic transition strategy, acknowledging that complete coverage takes time while ensuring the network remains immediately useful.</p><p>This is our second technical anchor—community-owned connectivity that flows where needed, that users deploy and control, that respects privacy while providing precision performance. Code and communication, both freed from centralized control, both healing through the same principles.</p><p>The pattern becomes clear. Coldriver Heal isn't just for software. It's a template for any system where community ownership matters, where precision and flow must combine, where regenerative cycles replace extractive monopolies. Codeberg for code. Helium for connectivity. More will follow.<h2></h2></p><h2>The Synthesis: Mathematical Ecology</h2><p>Now we synthesize. What happens when Hilbert's cold precision meets Schauberger's warm flow?</p><p>Consider the central paradox. Hilbert sought complete, decidable, consistent formal systems. Gödel proved that any system powerful enough to encode arithmetic will have unprovable truths. Schauberger observed emergent complexity arising from simple natural rules. Nature demonstrates self-organization without complete formalization. These seem like contradictions. They are not. They are complementary dualities, two sides of the same truth about how complex systems actually function.</p><p>Hilbert provides the stage. Think of a Hilbert space—an infinite-dimensional vector space, complete in the sense that every Cauchy sequence converges, equipped with an inner product that measures similarity and orthogonality. This is the mathematical stage on which our systems operate. Nock's twelve rules are basis vectors, irreducible and orthogonal operations from which everything else derives. Composition is linear combination of these basis operations. Programs are vectors in this space. Execution is operators transforming vectors, moving us from one point to another in the space of possible computations.</p><p>Schauberger provides the dance. Within this formal stage, how do we actually move? Not linearly. Not by brute force. But by natural flow patterns that have been proven across billions of years of evolution.</p><p>Consider s6 supervision as process vortices. Each service is a tributary stream, flowing independently yet contributing to the whole. The s6-svscan daemon is the spring, PID 1, the source from which all process supervision flows. s6-supervise watches each individual flow, ready to restart if it stops, maintaining the cycle. Crash-only design mirrors natural flood management—processes are like water, expected to flow and to stop, with the system designed for continuous evaporation and condensation, death and rebirth, without data loss.</p><p>Consider Grainstore dependencies as seed bank ecology. Curated species, each verified before inclusion. Regenerative cycles that rebuild from source specifications, not binary artifacts. Polyculture approach with diverse dependencies creating resilience. Closed-loop design requiring no external package registries. This is how nature stores genetic information—distributed, redundant, capable of regeneration from minimal input.</p><p>Consider regenesis builds as full water cycles. Specifications are springs, the eternal source that never dries up. Clojure code is river flow, derived from those specifications but free to meander and adapt. Tests are purification vortices, catching impurities before they propagate downstream. Jets are optimization channels, fast paths that preserve correctness through verified compilation. Built artifacts are the delta reaching the sea, stable deployments. And the next build is rain returning to the source, the cycle beginning again with renewed specifications.</p><p>The synthesis produces systems that are both provable and alive. Axiomatic systems that grow like ecosystems. They start with frozen axioms—Nock, Git, s6 specifications that do not change. They allow natural composition through vortex patterns and spiraling flows. They maintain formal correctness through proofs, tests, and type systems. They enable continuous regeneration through full cycles and regenesis builds that never stop.</p><p>Formal proofs that flow like water. Verification isn't one-shot; it's continuous, running in CI vortices with every push. Correctness isn't static; it regenerates, each build re-proving properties from first principles. Evidence accumulates like sediment, test coverage and git history building up in layers that future developers can excavate to understand how we arrived here.</p><p>Sovereign computing that completes dependency chains. Grainstore functions as both parts warehouse and seed bank. Equivalence notes provide botanical taxonomy, Nock models that classify and relate different implementations. Regenesis cycles implement perennial agriculture, continuously renewable. The result is systems that last generations, not quarters. Code that your grandchildren could still build from source.</p><p>And now you understand the Coldriver metaphor. Cold for Hilbert's precision, the frozen axioms that provide stability. Driver for directed control, not passive observation of natural systems but active cultivation of their patterns. But also col for the column of water in Schauberger's vortex funnel, the organized flow that purifies and energizes. And driver for that which drives regeneration—the vortex motion itself, the spiral that transforms input into verified output.</p><p>The Coldriver heals by directing flow with mathematical precision, by following natural patterns of regeneration, by maintaining cold axioms at four degrees Celsius where water is most dense and most organized, and by enabling warm cycles of life, growth, and continuous evolution within that framework.<h2></h2></p><h2>The Journey Ahead</h2><p>This essay establishes the philosophical foundation. The work continues through a series of writings that explore these ideas in greater depth. Essay 9299 will dive into Hilbert for programmers, making axiomatic thinking concrete with operators and proofs. Essay 9300 will explore Schauberger for systems designers, detailing vortex patterns, implosion dynamics, and natural flow in software architecture. Essay 9301 will provide a deep dive into Codeberg as the sovereign forge, showing how theory manifests in practice. Essay 9302 will examine Nock as computational axioms, the twelve frozen rules that form our bedrock.</p><p>These new writings then merge into the existing series at Essay 9499, \"The Valley Awaits,\" now enriched with this foundational philosophy. Everything we've already built gains deeper meaning.</p><p>The structured essays from 9499 to 9580, our foundation phase, can now be understood as building Hilbert spaces with mathematical rigor while implementing Schauberger flows with natural patterns. The narrative chronicles from 9948 to 9960, our journey stories, reveal characters as operators in our space and settings as vortex landscapes of learning. The Grainstore strategy emerges as both axiomatic, proven correct through formal methods, and ecological, regenerative through full cycles. SixOS on Framework 16 becomes the reference implementation where hardware provides the substrate, the Hilbert space itself; s6 supervision creates process vortices following Schauberger's principles; and builds implement regenesis cycles that heal from source.</p><p>But philosophy without practice is abstraction. How does this synthesis manifest in daily work?</p><p>When you write code, ask yourself: What are the axioms? Where are the fundamental truths this builds upon? Does this follow natural flow, or am I forcing water uphill? The result will be clear, maintainable, regenerative code that future developers can understand and modify without fear.</p><p>When you design systems, define frozen interfaces with cold precision, axioms that won't drift. Allow composition through natural patterns, letting components flow together rather than forcing rigid hierarchies. Enable continuous regeneration through healing cycles that rebuild from specifications rather than patching binaries.</p><p>When you choose dependencies, verify against specifications in the Hilbert sense—can you prove this does what it claims? Prefer closed-loop cycles in the Schauberger sense—does this complete its work and clean up after itself? Maintain them in Grainstore to preserve sovereignty, ensuring you can rebuild from source a decade from now.</p><p>When you debug, trace back to axioms to understand what was actually proven versus what was assumed. Look for incomplete cycles, places where flow could be improved or optimized. Regenerate from source, rebuilding components from specifications rather than patching, renewing through regenesis rather than accumulating modifications.</p><p>This philosophical foundation succeeds if technical readers find it rigorous and actionable, if philosophical readers find it inspiring and profound, if the metaphor feels inevitable rather than forced, if it clearly differentiates this approach from ad-hoc engineering, and if it provides practical guidance for the daily decisions that accumulate into systems.<h2></h2></p><h2>Conclusion: The Waters Are Crystalline, The Flows Are Clear</h2><p>We stand at a transition point in computing. A choice between two paths, two philosophies, two futures.</p><p>The first path continues as we have been. Ad-hoc systems that break with each dependency update. Explosion-based engineering that pushes outward with force, pressure, and waste. Monolithic platforms that decay from the moment they ship, requiring constant patches, security updates, and eventual rewrites. This is the path of technical debt accumulating faster than we can pay it down, of systems that last quarters instead of generations, of code that becomes unmaintainable before it becomes profitable.</p><p>The second path builds differently. Community-owned systems that regenerate from enduring specifications. Implosion-based design that pulls inward with suction, efficiency, and closed loops. Federated ecosystems that self-heal through distributed redundancy and formal verification. This is the path of technical assets that appreciate over time, of systems that your grandchildren could still build from source, of code that becomes clearer with age rather than more obscure.</p><p>The path forward requires both Hilbert's crystalline precision and Schauberger's warm flow. Well-formed specifications and formal proofs. Natural patterns and regenerative cycles. Crystalline axioms and warm life. Together, they produce something new. Coldriver Heal.</p><p>These are systems that start with axioms—Nock's twelve rules, Git's immutable objects, s6's process supervision contracts. They compose through vortices—CI pipelines that verify code, supervision trees that maintain service continuity, development flows that spiral through stages of refinement. They regenerate eternally, not through one-time genesis but through continuous regenesis that renews. They thrive through sovereignty that prevents vendor lock-in, closed loops that waste nothing, and determinism that makes the future predictable.</p><p>This is precision flow. Mathematical clarity finding its natural course. This is mathematical ecology. Formal systems that grow like living organisms. This is computing that lasts. Code written once, maintained for generations, rebuilt from source across centuries of hardware change.</p><p>The Coldriver heals through precision flow. The waters are crystalline—four degrees Celsius, where water is most dense, most organized, most mature, where Pollack's fourth phase reveals structure within flow. The flows are clear—directed by mathematics, following nature's patterns, spiraling through vortices of verification and emerging purified. And the healing has begun.</p><p>We have the tools. We have the principles. We have the examples. What remains is the work—the daily practice of building systems this way, the discipline of tracing back to axioms, the patience of letting flows find their natural course, the sovereignty of maintaining our own foundations.</p><p>The frozen specifications endure. The vortices purify. The cycles regenerate. The code heals.</p><p>This is the foundation. Now we build upon it.<h2></h2></p><h2>References & Further Reading</h2><h3>Hilbert's Mathematics</h3><ul><li>Hilbert, David. <em>Foundations of Geometry</em> (1899)</li><li>Hilbert's problems (1900) - particularly #2 (consistency of arithmetic)</li><li>Weyl, Hermann. <em>The Concept of a Hilbert Space</em></li><li>von Neumann, John. <em>Mathematical Foundations of Quantum Mechanics</em> (Hilbert spaces)</li></ul><h3>Schauberger's Ecology</h3><ul><li>Alexandersson, Olof. <em>Living Water: Viktor Schauberger and the Secrets of Natural Energy</em> (1982)</li><li>Coats, Callum. <em>Living Energies: An Exposition of Concepts Related to the Theories of Viktor Schauberger</em> (1996)</li><li>Schauberger, Viktor. <em>The Water Wizard</em> (collected writings)</li><li>Documentary: \"Viktor Schauberger - Comprehend and Copy Nature\" (2008)</li></ul><h3>Our Implementation</h3><ul><li><a href='/12025-10/9509-codeberg-precision-engineering-platform'>Essay 9509: Codeberg - Precision Engineering Platform</a></li><li><a href='/12025-10/9503-what-is-nock'>Essay 9503: What is Nock?</a> - The 12 frozen rules</li><li><a href='/12025-10/9514-sixos-framework-16-installation'>Essay 9514: SixOS Framework 16 Installation</a></li><li><a href='/12025-10/9515-regenesis-demo-make-it-tactile'>Essay 9515: Regenesis Demo</a></li><li><a href='../docs/VISION-SYNTHESIS-2025-10-11_7777.md'>Vision Synthesis Document</a></li></ul><h3>Related Concepts</h3><ul><li>Gödel's incompleteness theorems (limits of formalization)</li><li>Permaculture design (closed-loop systems)</li><li>Process calculi (π-calculus, ambient calculus)</li><li>Functional programming (immutability, composition)</li><li>Formal methods (TLA+, Coq, Isabelle)<h2></h2></li></ul><p><strong>Essay 9298 Complete</strong><br /> <strong>Word Count</strong>: ~3,200<br /> <strong>Date</strong>: 2025-10-11<br /> <strong>Series</strong>: Coldriver Heal (Philosophical Foundation)<br /> <strong>Next</strong>: Essay 9299 - \"Hilbert for Programmers\"</p><p>← Previous: <em>Start Here</em> | <strong>Foundation</strong> | Next: <a href='#'>9299 (Hilbert for Programmers)</a> →<h2></h2></p><p><em>This essay establishes the philosophical foundation for the Coldriver Heal project. All subsequent technical decisions derive from these principles: cold precision (Hilbert), warm flow (Schauberger), continuous healing (regenesis). The waters are cold. The flows are clear. The work continues.</em></p><p><em><a href='/12025-10/hidden-docs-index.html'>View Hidden Docs Index</a></em> | <em><a href='/12025-10/'>Return to Main Index</a></em></p>",
  "hash" : "2025-10-22T15:17:39.427550939Z-33205"
}